{
  "categories": [],
  "content": "Short selling & Put options are bearish ways of speculation",
  "created": "2023-01-29T18:32:28.500Z",
  "guideIntegrations": {
    "discordRoleIds": []
  },
  "guideType": "onboarding",
  "key": "bearish-short-vs-put-dodao-academy",
  "name": "Bearish - Short vs Put",
  "publishStatus": "Draft",
  "showIncorrectOnCompletion": true,
  "steps": [
    {
      "content": "## Overview\nShort selling and put options are basically bearish strategies used to speculate on the possible decline of the underlying security or index. These strategies are also useful for hedging the downside risk of a portfolio or specific stocks. Although these two investment methods have common characteristics, there are also differences that investors should understand.\n\n## Short Selling\nShort selling is the sale of securities that the seller does not own, but has borrowed, in the market and buys them back later, which can result in significant losses if the market rises. \n\n\n## Put Option\nPurchasing a put option gives the purchaser the right to sell the underlying asset at the price specified in the option with the maximum loss being the premium paid for the option.",
      "name": "Introduction",
      "stepItems": [],
      "uuid": "81c87ab5-011e-46e3-8c2f-4e5ead0c5c3d"
    },
    {
      "content": "",
      "name": "Introduction Evaluation",
      "stepItems": [],
      "uuid": "36150ca7-e52c-495d-ad2f-0c4735284a85"
    }
  ],
  "thumbnail": "https://d31h13bdjwgzxs.cloudfront.net/QmWy8EeMnxqx96VEPx2NBwzqtKxvMQqVVYvmPKgAYS2cUi",
  "uuid": "bearish-short-vs-put-dodao-academy"
}